odoo/addons/website_event_filter_selector/README.rst
odoo/addons/website_event_filter_selector/__init__.py
odoo/addons/website_event_filter_selector/__manifest__.py
odoo/addons/website_event_filter_selector/controllers/__init__.py
odoo/addons/website_event_filter_selector/controllers/main.py
odoo/addons/website_event_filter_selector/demo/assets.xml
odoo/addons/website_event_filter_selector/i18n/de.po
odoo/addons/website_event_filter_selector/i18n/es.po
odoo/addons/website_event_filter_selector/i18n/website_event_filter_selector.pot
odoo/addons/website_event_filter_selector/images/all.png
odoo/addons/website_event_filter_selector/images/choose.png
odoo/addons/website_event_filter_selector/models/__init__.py
odoo/addons/website_event_filter_selector/models/event.py
odoo/addons/website_event_filter_selector/readme/CONFIGURE.rst
odoo/addons/website_event_filter_selector/readme/CONTRIBUTORS.rst
odoo/addons/website_event_filter_selector/readme/DESCRIPTION.rst
odoo/addons/website_event_filter_selector/readme/ROADMAP.rst
odoo/addons/website_event_filter_selector/static/description/icon.png
odoo/addons/website_event_filter_selector/static/description/index.html
odoo/addons/website_event_filter_selector/static/src/js/website_event_filter_selector.js
odoo/addons/website_event_filter_selector/static/src/js/website_event_filter_selector.tour.js
odoo/addons/website_event_filter_selector/templates/assets.xml
odoo/addons/website_event_filter_selector/templates/event.xml
odoo/addons/website_event_filter_selector/tests/__init__.py
odoo/addons/website_event_filter_selector/tests/test_ui.py
odoo11_addon_website_event_filter_selector-11.0.1.0.0.99.dev5.dist-info/METADATA
odoo11_addon_website_event_filter_selector-11.0.1.0.0.99.dev5.dist-info/WHEEL
odoo11_addon_website_event_filter_selector-11.0.1.0.0.99.dev5.dist-info/top_level.txt
odoo11_addon_website_event_filter_selector-11.0.1.0.0.99.dev5.dist-info/RECORD
